CHANGES.rst
DESCRIPTION.rst
LICENSE
MANIFEST.in
README.md
setup.py
src/idc/paddle/__init__.py
src/idc/paddle/class_lister.py
src/idc/paddle/reader/__init__.py
src/idc/paddle/reader/imgcls/__init__.py
src/idc/paddle/reader/imgcls/_paddle.py
src/idc/paddle/reader/imgseg/__init__.py
src/idc/paddle/reader/imgseg/_paddle.py
src/idc/paddle/writer/__init__.py
src/idc/paddle/writer/imgcls/__init__.py
src/idc/paddle/writer/imgcls/_paddle.py
src/idc/paddle/writer/imgseg/__init__.py
src/idc/paddle/writer/imgseg/_paddle.py
src/image_dataset_converter_paddle.egg-info/PKG-INFO
src/image_dataset_converter_paddle.egg-info/SOURCES.txt
src/image_dataset_converter_paddle.egg-info/dependency_links.txt
src/image_dataset_converter_paddle.egg-info/entry_points.txt
src/image_dataset_converter_paddle.egg-info/requires.txt
src/image_dataset_converter_paddle.egg-info/top_level.txt