Metadata-Version: 2.1
Name: image-dataset-converter-paddle
Version: 0.0.4
Summary: image-dataset-converter plugins for Paddle (PArallel Distributed Deep LEarning).
Home-page: https://github.com/waikato-datamining/image-dataset-converter-paddle
Author: Peter Reutemann
Author-email: fracpete@waikato.ac.nz
License: MIT License
Classifier: Development Status :: 4 - Beta
Classifier: License :: OSI Approved :: MIT License
Classifier: Topic :: Scientific/Engineering :: Artificial Intelligence
Classifier: Topic :: Scientific/Engineering :: Image Processing
License-File: LICENSE
